agit/__init__.py
agit/cls.py
agit/common.py
agit/embd.py
agit/eval.py
agit/llm.py
agit/utils.py
agit/backend/__init__.py
agit/backend/local.py
agit/backend/openai_bk.py
agit/backend/zhipu_api.py
agit/backend/zhipuai_bk.py
agit-0.1.42.dist-info/METADATA
agit-0.1.42.dist-info/WHEEL
agit-0.1.42.dist-info/top_level.txt
agit-0.1.42.dist-info/zip-safe
agit-0.1.42.dist-info/RECORD
