Metadata-Version: 2.1
Name: agit
Version: 0.1.42
Summary: tools for agi
Home-page: https://github.com/jerrychen1990/agi-tools.git
Author: Chen Hao
Author-email: jerrychen1990@gmail.com
License: MIT
Requires-Dist: zhipuai
Requires-Dist: openai
Requires-Dist: python-snippets
Requires-Dist: click
Requires-Dist: scipy
Requires-Dist: pandas
Requires-Dist: loguru
